ScriptorQL/__init__.py
ScriptorQL/script.py
data_to_sql_insert/__init__.py
data_to_sql_insert/core.py
data_to_sql_insert/script.py
ScriptorQL-0.0.3.dist-info/LICENSE
ScriptorQL-0.0.3.dist-info/METADATA
ScriptorQL-0.0.3.dist-info/WHEEL
ScriptorQL-0.0.3.dist-info/top_level.txt
ScriptorQL-0.0.3.dist-info/RECORD
