Metadata-Version: 2.1
Name: ScriptorQL
Version: 0.0.3
Summary: Generates SQL insert values script for data
Home-page: https://github.com/FortuneCandy/ScriptorQL
Author: Arne Goossens
Author-email: FortuneCandy99@gmail.com
License: GNU GENERAL PUBLIC LICENSE Version 3
Keywords: Generate SQL insert values script
Platform: UNKNOWN
Classifier: Development Status :: 3 - Alpha
Classifier: Topic :: Utilities
Classifier: License :: OSI Approved :: GNU General Public License v3 (GPLv3)
Classifier: Programming Language :: Python :: 3
Classifier: Operating System :: OS Independent
